collagram.py
setup.py
collagram.egg-info/PKG-INFO
collagram.egg-info/SOURCES.txt
collagram.egg-info/dependency_links.txt
collagram.egg-info/not-zip-safe
collagram.egg-info/requires.txt
collagram.egg-info/top_level.txt