Metadata-Version: 1.0
Name: collagram
Version: 0.7.1
Summary: Generate collages of Instagram photographs.
Home-page: http://github.com/vurbmedia/collagram/
Author: Adam Patterson
Author-email: adam@adamrt.com
License: ISC
Platform: any
